Laravel4/README.md
Laravel4/__init__.py
Laravel4/__main__.py
Laravel4/file.epub
Laravel4/index.html
Laravel4/css/__init__.py
Laravel4/css/annotations.css
Laravel4/css/main.css
Laravel4/css/normalize.css
Laravel4/css/popup.css
Laravel4/font/__init__.py
Laravel4/font/fontello.eot
Laravel4/font/fontello.svg
Laravel4/font/fontello.ttf
Laravel4/font/fontello.woff
Laravel4/img/__init__.py
Laravel4/img/annotator-glyph-sprite.png
Laravel4/img/annotator-icon-sprite.png
Laravel4/img/apple-touch-icon.png
Laravel4/img/cancelfullscreen.png
Laravel4/img/close.png
Laravel4/img/fullscreen.png
Laravel4/img/loader.gif
Laravel4/img/menu-icon.png
Laravel4/img/save.png
Laravel4/img/saved.png
Laravel4/img/settings-s.png
Laravel4/img/settings.png
Laravel4/img/star.png
Laravel4/js/__init__.py
Laravel4/js/epub.js
Laravel4/js/epub.min.js
Laravel4/js/epub.min.map
Laravel4/js/hooks.min.js
Laravel4/js/hooks.min.map
Laravel4/js/reader.js
Laravel4/js/reader.js.map
Laravel4/js/reader.min.js
Laravel4/js/reader.min.map
Laravel4/js/hooks/__init__.py
Laravel4/js/hooks/extensions/__init__.py
Laravel4/js/hooks/extensions/highlight.js
Laravel4/js/libs/__init__.py
Laravel4/js/libs/jquery.min.js
Laravel4/js/libs/localforage.min.js
Laravel4/js/libs/screenfull.js
Laravel4/js/libs/screenfull.min.js
Laravel4/js/libs/zip.min.js
Laravel4/js/plugins/__init__.py
Laravel4/js/plugins/hypothesis.js
Laravel4/js/plugins/search.js
laravel_4-2024.3.1.0.dist-info/METADATA
laravel_4-2024.3.1.0.dist-info/WHEEL
laravel_4-2024.3.1.0.dist-info/entry_points.txt
laravel_4-2024.3.1.0.dist-info/top_level.txt
laravel_4-2024.3.1.0.dist-info/RECORD
